[
    {
        "imdb_id": "tt0108052",
        "title": "Schindler's List"
    },
    {
        "imdb_id": "tt0108065",
        "title": "Searching for Bobby Fischer"
    },
    {
        "imdb_id": "tt0107688",
        "title": "The Nightmare Before Christmas"
    },
    {
        "imdb_id": "tt0107048",
        "title": "Groundhog Day"
    },
    {
        "imdb_id": "tt0106977",
        "title": "The Fugitive"
    },
    {
        "imdb_id": "tt0107290",
        "title": "Jurassic Park"
    },
    {
        "imdb_id": "tt0107206",
        "title": "In the Line of Fire"
    },
    {
        "imdb_id": "tt0108394",
        "title": "Three Colors: Blue"
    },
    {
        "imdb_id": "tt0108551",
        "title": "What's Love Got to Do with It"
    },
    {
        "imdb_id": "tt8531222",
        "title": "Dave"
    },
    {
        "imdb_id": "tt0108122",
        "title": "Short Cuts"
    },
    {
        "imdb_id": "tt0107943",
        "title": "The Remains of the Day"
    },
    {
        "imdb_id": "tt0107207",
        "title": "In the Name of the Father"
    },
    {
        "imdb_id": "tt0108399",
        "title": "True Romance"
    },
    {
        "imdb_id": "tt0106677",
        "title": "Dazed and Confused"
    },
    {
        "imdb_id": "tt0107822",
        "title": "The Piano"
    },
    {
        "imdb_id": "tt0107282",
        "title": "The Joy Luck Club"
    },
    {
        "imdb_id": "tt0107616",
        "title": "Much Ado About Nothing"
    },
    {
        "imdb_id": "tt0108550",
        "title": "What's Eating Gilbert Grape"
    },
    {
        "imdb_id": "tt0107653",
        "title": "Naked"
    },
    {
        "imdb_id": "tt2702920",
        "title": "The Secret Garden"
    },
    {
        "imdb_id": "tt0103873",
        "title": "Dead Alive"
    },
    {
        "imdb_id": "tt0107756",
        "title": "Orlando"
    },
    {
        "imdb_id": "tt0106226",
        "title": "The Age of Innocence"
    },
    {
        "imdb_id": "tt5973164",
        "title": "Fearless"
    },
    {
        "imdb_id": "tt0106519",
        "title": "Carlito's Way"
    },
    {
        "imdb_id": "tt0472954",
        "title": "It's Always Sunny in Philadelphia"
    },
    {
        "imdb_id": "tt0108002",
        "title": "Rudy"
    },
    {
        "imdb_id": "tt0106220",
        "title": "Addams Family Values"
    },
    {
        "imdb_id": "tt0108160",
        "title": "Sleepless in Seattle"
    },
    {
        "imdb_id": "tt0106918",
        "title": "The Firm"
    },
    {
        "imdb_id": "tt0106611",
        "title": "Cool Runnings"
    },
    {
        "imdb_id": "tt0106387",
        "title": "Benny & Joon"
    },
    {
        "imdb_id": "tt0108358",
        "title": "Tombstone"
    },
    {
        "imdb_id": "tt0106856",
        "title": "Falling Down"
    },
    {
        "imdb_id": "tt0106308",
        "title": "Army of Darkness"
    },
    {
        "imdb_id": "tt0107614",
        "title": "Mrs. Doubtfire"
    },
    {
        "imdb_id": "tt0106582",
        "title": "Cliffhanger"
    },
    {
        "imdb_id": "tt0110950",
        "title": "Reality Bites"
    },
    {
        "imdb_id": "tt0108037",
        "title": "The Sandlot"
    },
    {
        "imdb_id": "tt0107050",
        "title": "Grumpy Old Men"
    },
    {
        "imdb_id": "tt0108525",
        "title": "Wayne's World 2"
    },
    {
        "imdb_id": "tt0106697",
        "title": "Demolition Man"
    },
    {
        "imdb_id": "tt0107798",
        "title": "The Pelican Brief"
    },
    {
        "imdb_id": "tt0109040",
        "title": "Ace Ventura: Pet Detective"
    },
    {
        "imdb_id": "tt0107120",
        "title": "Hocus Pocus"
    },
    {
        "imdb_id": "tt0107977",
        "title": "Robin Hood: Men in Tights"
    },
    {
        "imdb_id": "tt0107362",
        "title": "Last Action Hero"
    },
    {
        "imdb_id": "tt0107211",
        "title": "Indecent Proposal"
    },
    {
        "imdb_id": "tt0107969",
        "title": "Rising Sun"
    },
    {
        "imdb_id": "tt0108255",
        "title": "Super Mario Bros."
    }
]