[
    {
        "imdb_id": "tt1024648",
        "title": "Argo"
    },
    {
        "imdb_id": "tt1074638",
        "title": "Skyfall"
    },
    {
        "imdb_id": "tt0848228",
        "title": "The Avengers"
    },
    {
        "imdb_id": "tt1748122",
        "title": "Moonrise Kingdom"
    },
    {
        "imdb_id": "tt1276104",
        "title": "Looper"
    },
    {
        "imdb_id": "tt1259521",
        "title": "The Cabin in the Woods"
    },
    {
        "imdb_id": "tt1772925",
        "title": "Jiro Dreams of Sushi"
    },
    {
        "imdb_id": "tt1045658",
        "title": "Silver Linings Playbook"
    },
    {
        "imdb_id": "tt1345836",
        "title": "The Dark Knight Rises"
    },
    {
        "imdb_id": "tt1602620",
        "title": "Amour"
    },
    {
        "imdb_id": "tt2120152",
        "title": "The Invisible War"
    },
    {
        "imdb_id": "tt2011971",
        "title": "Monsieur Lazhar"
    },
    {
        "imdb_id": "tt1827512",
        "title": "The Kid with a Bike"
    },
    {
        "imdb_id": "tt1845773",
        "title": "Ai Weiwei: Never Sorry"
    },
    {
        "imdb_id": "tt2124803",
        "title": "How to Survive a Plague"
    },
    {
        "imdb_id": "tt1568921",
        "title": "The Secret World of Arrietty"
    },
    {
        "imdb_id": "tt1667905",
        "title": "Dies ist kein Film"
    },
    {
        "imdb_id": "tt0443272",
        "title": "Lincoln"
    },
    {
        "imdb_id": "tt2125608",
        "title": "Searching for Sugar Man"
    },
    {
        "imdb_id": "tt1316536",
        "title": "The Loved Ones"
    },
    {
        "imdb_id": "tt1860355",
        "title": "Undefeated"
    },
    {
        "imdb_id": "tt1931388",
        "title": "Beware of Mr. Baker"
    },
    {
        "imdb_id": "tt2111478",
        "title": "Mea Maxima Culpa: Silence in the House of God"
    },
    {
        "imdb_id": "tt2076220",
        "title": "Holy Motors"
    },
    {
        "imdb_id": "tt1990352",
        "title": "The Island President"
    },
    {
        "imdb_id": "tt2125666",
        "title": "The Queen of Versailles"
    },
    {
        "imdb_id": "tt1736633",
        "title": "Oslo, August 31st"
    },
    {
        "imdb_id": "tt2130321",
        "title": "West of Memphis"
    },
    {
        "imdb_id": "tt1966604",
        "title": "The Imposter"
    },
    {
        "imdb_id": "tt1183919",
        "title": "Marley"
    },
    {
        "imdb_id": "tt1866249",
        "title": "The Sessions"
    },
    {
        "imdb_id": "tt1853728",
        "title": "Django Unchained"
    },
    {
        "imdb_id": "tt1579361",
        "title": "Chasing Ice"
    },
    {
        "imdb_id": "tt7541720",
        "title": "Music"
    },
    {
        "imdb_id": "tt0067541",
        "title": "Wake in Fright"
    },
    {
        "imdb_id": "tt1800266",
        "title": "Brooklyn Castle"
    },
    {
        "imdb_id": "tt2125423",
        "title": "5 Broken Cameras"
    },
    {
        "imdb_id": "tt2073029",
        "title": "Marina Abramovic: The Artist Is Present"
    },
    {
        "imdb_id": "tt0454876",
        "title": "Life of Pi"
    },
    {
        "imdb_id": "tt2178941",
        "title": "Barbara"
    },
    {
        "imdb_id": "tt1862079",
        "title": "Safety Not Guaranteed"
    },
    {
        "imdb_id": "tt1614989",
        "title": "Jo Nesb\u00f8's Headhunters"
    },
    {
        "imdb_id": "tt1392170",
        "title": "The Hunger Games"
    },
    {
        "imdb_id": "tt2053352",
        "title": "Diana Vreeland: The Eye Has to Travel"
    },
    {
        "imdb_id": "tt2125653",
        "title": "The House I Live In"
    },
    {
        "imdb_id": "tt1925421",
        "title": "Elena"
    },
    {
        "imdb_id": "tt1623288",
        "title": "ParaNorman"
    },
    {
        "imdb_id": "tt1787797",
        "title": "Sing Your Song"
    },
    {
        "imdb_id": "tt1753813",
        "title": "Farewell, My Queen"
    },
    {
        "imdb_id": "tt1142977",
        "title": "Frankenweenie"
    },
    {
        "imdb_id": "tt2008513",
        "title": "First Position"
    },
    {
        "imdb_id": "tt1650453",
        "title": "I Wish"
    },
    {
        "imdb_id": "tt2014338",
        "title": "Side by Side"
    },
    {
        "imdb_id": "tt1827487",
        "title": "Once Upon a Time in Anatolia"
    },
    {
        "imdb_id": "tt2380247",
        "title": "The Central Park Five"
    },
    {
        "imdb_id": "tt1764183",
        "title": "Arbitrage"
    },
    {
        "imdb_id": "tt1971352",
        "title": "Compliance"
    },
    {
        "imdb_id": "tt1772341",
        "title": "Wreck-It Ralph"
    },
    {
        "imdb_id": "tt1704573",
        "title": "Bernie"
    },
    {
        "imdb_id": "tt1650407",
        "title": "Turn Me On, Dammit!"
    },
    {
        "imdb_id": "tt2190367",
        "title": "Neighboring Sounds"
    },
    {
        "imdb_id": "tt1560747",
        "title": "The Master"
    },
    {
        "imdb_id": "tt1276419",
        "title": "A Royal Affair"
    },
    {
        "imdb_id": "tt2125435",
        "title": "Beasts of the Southern Wild"
    },
    {
        "imdb_id": "tt1445520",
        "title": "Footnote"
    },
    {
        "imdb_id": "tt1232829",
        "title": "21 Jump Street"
    },
    {
        "imdb_id": "tt1899353",
        "title": "The Raid: Redemption"
    },
    {
        "imdb_id": "tt1659337",
        "title": "The Perks of Being a Wallflower"
    },
    {
        "imdb_id": "tt2125501",
        "title": "Electric Boogaloo: The Wild, Untold Story of Cannon Films"
    },
    {
        "imdb_id": "tt2011953",
        "title": "Keep the Lights On"
    },
    {
        "imdb_id": "tt1706593",
        "title": "Chronicle"
    },
    {
        "imdb_id": "tt5164184",
        "title": "In Darkness"
    },
    {
        "imdb_id": "tt1855199",
        "title": "End of Watch"
    },
    {
        "imdb_id": "tt1430626",
        "title": "The Pirates! Band of Misfits"
    },
    {
        "imdb_id": "tt1931533",
        "title": "Seven Psychopaths"
    },
    {
        "imdb_id": "tt1990314",
        "title": "Robot & Frank"
    },
    {
        "imdb_id": "tt1922645",
        "title": "The Fairy"
    },
    {
        "imdb_id": "tt2043931",
        "title": "Neil Young Journeys"
    },
    {
        "imdb_id": "tt1316540",
        "title": "The Turin Horse"
    },
    {
        "imdb_id": "tt0242193",
        "title": "Bully"
    },
    {
        "imdb_id": "tt2035630",
        "title": "Starlet"
    },
    {
        "imdb_id": "tt1661420",
        "title": "Polisse"
    },
    {
        "imdb_id": "tt3647998",
        "title": "Taboo"
    },
    {
        "imdb_id": "tt1821593",
        "title": "Rundskop"
    },
    {
        "imdb_id": "tt0482374",
        "title": "Gone"
    },
    {
        "imdb_id": "tt1560139",
        "title": "Boy"
    },
    {
        "imdb_id": "tt1235830",
        "title": "Chico & Rita"
    },
    {
        "imdb_id": "tt5941692",
        "title": "Miss Bala"
    },
    {
        "imdb_id": "tt1473063",
        "title": "The Well Digger's Daughter"
    },
    {
        "imdb_id": "tt1649419",
        "title": "The Impossible"
    },
    {
        "imdb_id": "tt1742336",
        "title": "Your Sister's Sister"
    },
    {
        "imdb_id": "tt2053425",
        "title": "Rust and Bone"
    },
    {
        "imdb_id": "tt1291652",
        "title": "Easy Money"
    },
    {
        "imdb_id": "tt2077851",
        "title": "Sleepwalk with Me"
    },
    {
        "imdb_id": "tt1217209",
        "title": "Brave"
    },
    {
        "imdb_id": "tt1506999",
        "title": "Haywire"
    },
    {
        "imdb_id": "tt1915581",
        "title": "Magic Mike"
    },
    {
        "imdb_id": "tt1907668",
        "title": "Flight"
    },
    {
        "imdb_id": "tt0096926",
        "title": "The Big Picture"
    },
    {
        "imdb_id": "tt2125490",
        "title": "Detropia"
    }
]